{
  "slug": "virtual-threads-structured-concurrency",
  "title": "Virtual Threads Are Not Enough: Why Structured Concurrency Changes How You Reason About Concurrent Code",
  "description": "Virtual threads solve throughput. Structured concurrency solves correctness. This article explains why the second half of Project Loom matters more for writing concurrent code you can actually reason about.",
  "tags": [
    "Concurrency",
    "Java",
    "Project Loom",
    "JDK 21"
  ],
  "readTime": "14 min",
  "publishedAt": "2026-04-24",
  "content": "## The Problem Nobody Talks About\n\nMost of the noise around Project Loom focuses on virtual threads: you can now spin up a million threads without exhausting memory, blocking I/O no longer parks your carrier thread, and you can throw away your thread pools for most workloads. That's a real win.\n\nBut virtual threads alone do not fix the hardest part of concurrent programming. They make it cheaper to be concurrent — they do not make it easier to be **correct**.\n\nConsider this pattern you've probably written or reviewed:\n\n```java\nExecutorService executor = Executors.newVirtualThreadPerTaskExecutor();\n\nFuture<UserProfile> profileFuture = executor.submit(() -> fetchUserProfile(userId));\nFuture<List<Order>> ordersFuture = executor.submit(() -> fetchOrders(userId));\nFuture<List<Recommendation>> recsFuture = executor.submit(() -> fetchRecommendations(userId));\n\nUserProfile profile = profileFuture.get();\nList<Order> orders = ordersFuture.get();\nList<Recommendation> recs = recsFuture.get();\n```\n\nThree parallel calls. Looks clean. Now ask yourself: what happens if `fetchOrders` throws an exception? `profileFuture` and `recsFuture` are still running. The executor doesn't know these three tasks are logically one unit. You've forked three threads that are now orphaned — consuming resources, potentially writing to shared state, hitting downstream services — with no coordinated way to cancel them.\n\nThis is the structural problem that Structured Concurrency (finalized in JDK 21 as a preview, promoted in JDK 24) was designed to solve.\n\n---\n\n## What Structured Concurrency Actually Means\n\nThe core idea is borrowed from structured programming. When Dijkstra argued against GOTO, the insight was that control flow should have clear entry and exit points — a block of code enters, does its work, and exits as a unit. You can reason about it.\n\nStructured concurrency applies this to threads: **a group of concurrent tasks should have the same lifetime as the scope that created them**. A task scope opens, spawns subtasks, and closes. When the scope closes, all subtasks are either done or cancelled. No subtask outlives its scope.\n\nIn Java, this looks like:\n\n```java\ntry (var scope = new StructuredTaskScope.ShutdownOnFailure()) {\n    Subtask<UserProfile> profileTask = scope.fork(() -> fetchUserProfile(userId));\n    Subtask<List<Order>> ordersTask = scope.fork(() -> fetchOrders(userId));\n    Subtask<List<Recommendation>> recsTask = scope.fork(() -> fetchRecommendations(userId));\n\n    scope.join();           // wait for all subtasks\n    scope.throwIfFailed();  // propagate first failure\n\n    return new DashboardData(\n        profileTask.get(),\n        ordersTask.get(),\n        recsTask.get()\n    );\n}\n```\n\nThe difference isn't just syntax. The semantics are fundamentally different:\n\n- If any subtask fails, `ShutdownOnFailure` cancels the remaining tasks and the failure is propagated cleanly.\n- When the `try` block exits — for any reason — the scope's `close()` method guarantees all subtasks have completed or been cancelled before the enclosing code continues.\n- The call tree in a thread dump is meaningful again. A subtask's parent scope is visible.\n\n---\n\n## Two Policies, Two Different Contracts\n\n`StructuredTaskScope` ships with two built-in subclasses that cover most production use cases.\n\n### ShutdownOnFailure\n\nAll subtasks run. If any fails, the remaining are cancelled. The caller receives the first exception.\n\nUse this when you need **all results** and a single failure makes the whole operation invalid — fetching data to render a dashboard, for example, where a partial response would be worse than no response.\n\n```java\ntry (var scope = new StructuredTaskScope.ShutdownOnFailure()) {\n    Subtask<String> a = scope.fork(() -> callServiceA());\n    Subtask<String> b = scope.fork(() -> callServiceB());\n\n    scope.join().throwIfFailed();\n\n    return process(a.get(), b.get());\n}\n```\n\n### ShutdownOnSuccess\n\nSubtasks race. The first success cancels the rest. The scope returns that result.\n\nUse this when you have **redundant data sources** — multiple read replicas, fallback providers, or hedged requests — and you want the fastest one.\n\n```java\ntry (var scope = new StructuredTaskScope.ShutdownOnSuccess<PriceQuote>()) {\n    scope.fork(() -> fetchFromProviderA(item));\n    scope.fork(() -> fetchFromProviderB(item));\n    scope.fork(() -> fetchFromProviderC(item));\n\n    scope.join();\n    return scope.result();  // whichever finished first\n}\n```\n\nIf all fail, `scope.result()` throws. You can catch and handle it like any exception.\n\n---\n\n## A Realistic Example: Order Placement with Timeout\n\nHere's a more production-shaped example. Placing an order requires validating inventory, reserving payment, and sending a notification. Inventory and payment are critical — if either fails, the order cannot proceed. The notification is best-effort.\n\n```java\npublic OrderConfirmation placeOrder(OrderRequest request) throws Exception {\n    try (var scope = new StructuredTaskScope.ShutdownOnFailure()) {\n        Subtask<InventoryResult> inventory =\n            scope.fork(() -> inventoryService.reserve(request.items()));\n        Subtask<PaymentResult> payment =\n            scope.fork(() -> paymentService.authorize(request.payment()));\n\n        // Deadline: fail fast if critical services are slow\n        scope.joinUntil(Instant.now().plusSeconds(3));\n        scope.throwIfFailed();\n\n        // Both succeeded — notify asynchronously but don't let it block\n        notificationService.sendAsync(request.userId());\n\n        return new OrderConfirmation(inventory.get(), payment.get());\n    }\n}\n```\n\nA few things worth noting here:\n\n`joinUntil(Instant)` accepts a deadline. If the deadline passes before all tasks complete, the scope cancels remaining tasks and `throwIfFailed()` surfaces a `TimeoutException` (or whatever failed first). You don't need to wrap calls in `CompletableFuture.orTimeout()` or juggle `ScheduledFuture` handles.\n\nThe notification call is intentionally left outside the scope. It's fire-and-forget. If you want timeout + cancellation on it too, wrap it in its own scope.\n\n---\n\n## How This Interacts with Virtual Threads\n\nStructured concurrency is designed to work with virtual threads. When you call `scope.fork()`, the task runs on a virtual thread by default (from JDK 21 onward, the default factory is virtual). This means:\n\n- Blocking I/O inside subtasks doesn't park a carrier thread.\n- You can fork hundreds of subtasks without thread pool sizing concerns.\n- Stack traces remain meaningful — the virtual thread's stack shows the actual call chain.\n\nThe combination produces something you haven't had before in Java: **concurrent I/O at scale, with the code clarity of synchronous code, and the safety of bounded lifetimes**.\n\nCompare the mental model:\n\n| Approach | Throughput | Safety | Debuggability |\n|---|---|---|---|\n| Thread pool + Future | Medium | Poor (orphaned tasks) | Hard |\n| CompletableFuture chain | High | Moderate (tricky cancellation) | Painful |\n| Virtual threads alone | Very high | Poor (same as Future) | Moderate |\n| Structured concurrency + virtual threads | Very high | Strong (scoped lifetimes) | Good |\n\n---\n\n## Design Insights and Where to Be Careful\n\n**Nesting scopes is fine — but think about failure propagation.** Scopes can be nested. A subtask can open its own scope. This composes naturally, but you need to think about which exceptions bubble up and at what level you want to handle them.\n\n**Don't use it as a ThreadPoolExecutor replacement everywhere.** Structured concurrency is for *bounded* fan-out: you know the subtasks, you wait for them, the scope closes. Long-running background workers, event loops, or producer-consumer queues are not a good fit. Use virtual thread executors for those.\n\n**Interruption semantics matter.** When a scope shuts down, it interrupts its subtasks. If your task code ignores `InterruptedException` (a very common bug), cancellation won't propagate correctly. Always either re-interrupt the thread or let `InterruptedException` propagate.\n\n```java\n// Wrong: swallows interruption, task won't cancel\nscope.fork(() -> {\n    try {\n        return callExternalService();\n    } catch (InterruptedException e) {\n        return null; // bad\n    }\n});\n\n// Right: let it propagate\nscope.fork(() -> callExternalService()); // throws InterruptedException naturally\n```\n\n**Custom policies are possible.** The base class `StructuredTaskScope` is extensible. You can override `handleComplete(Subtask<?>)` to implement custom shutdown logic — for example, fail if more than N subtasks fail, or succeed if at least K out of N succeed (useful for quorum reads).\n\n---\n\n## Interview Perspective\n\nIf you're preparing for system design interviews at product companies, structured concurrency is a strong signal. Most interviewers have asked \"how would you make three parallel service calls?\" for years. The expected answer was CompletableFuture chains or a counted-down latch. Knowing that JDK 21 introduced a cleaner model — and being able to explain *why* it's safer — positions you as someone who tracks the platform.\n\nMore importantly, the underlying concept applies regardless of language: scoped lifetimes for concurrent tasks, failure propagation, cancellation. These principles show up in Kotlin coroutines (structured concurrency was popularized there), Go's context cancellation, and Rust's async task trees.\n\nIn an interview, lead with the problem: unscoped tasks lead to resource leaks and difficult cancellation. Then present the solution. Code can follow naturally.\n\n---\n\n## Key Takeaways\n\n- Virtual threads solve the cost of blocking I/O. Structured concurrency solves the correctness of concurrent task lifetimes.\n- `StructuredTaskScope` enforces that no subtask outlives its enclosing scope — analogous to lexical scoping in structured programming.\n- `ShutdownOnFailure` is for \"all must succeed\" fan-out. `ShutdownOnSuccess` is for \"fastest wins\" hedging.\n- Deadlines are first-class via `joinUntil(Instant)` — no need for external timeout wrappers.\n- Interruption must propagate correctly for cancellation to work. Never swallow `InterruptedException` in subtasks.\n- Custom policies can be built by extending the base class — useful for quorum patterns or partial failure tolerance.\n- The design philosophy is directly transferable: structured concurrency, scoped cancellation, and bounded task lifetimes are platform-agnostic ideas worth internalizing.\n\n---\n\n## Extending Further\n\nIf structured concurrency resonates with you, the next concepts to explore are:\n\n**Scoped values (JEP 446)** — a replacement for ThreadLocal that works cleanly with virtual threads and structured concurrency. Scoped values are immutable and inherited by subtasks, making it straightforward to pass request-scoped context (trace IDs, auth tokens) through a fork tree without the mutability hazards of ThreadLocal.\n\n**Cancellation tokens** — for long-running subtasks that poll or loop, checking `Thread.currentThread().isInterrupted()` periodically is the right pattern. Combine with a tight `joinUntil` deadline for hard SLA enforcement.\n\n**Reactive vs. structured** — if you're currently using Project Reactor or RxJava, structured concurrency covers a large portion of fan-out and aggregation patterns without the operator overhead. For event-driven streaming scenarios, reactive still wins. The two are complementary, not opposed.\n"
}